{"students/1793694/homework01/program02.py": [{"type": "function", "rank": "C", "col_offset": 0, "name": "conv", "endline": 164, "complexity": 14, "lineno": 98, "closures": []}, {"type": "function", "rank": "C", "col_offset": 0, "name": "suppfinale", "endline": 97, "complexity": 11, "lineno": 61, "closures": []}, {"type": "function", "rank": "B", "col_offset": 0, "name": "suppud", "endline": 45, "complexity": 6, "lineno": 37, "closures": []}, {"type": "function", "rank": "A", "col_offset": 0, "name": "suppc", "endline": 56, "complexity": 4, "lineno": 47, "closures": []}, {"type": "function", "rank": "A", "col_offset": 0, "name": "suppm", "endline": 36, "complexity": 3, "lineno": 32, "closures": []}]}
